Workbook

Sheet 00 Dashboard
A1: TURMERIC VALUE CHAIN OPTIMISER – KALAHANDI
A2: Purpose: maximise farmer and women SHG earnings while keeping market price, demand and investment realistic. Seba Jagat is treated as facilitator, not a profit centre.
A4: Scenario selector | B4: Balanced Farmer + SHG Benefit | D4: Scenario buttons are implemented as a dropdown in B4. Choose: Max Farmer, Max SHG, Lowest Investment, Market Penetration, Retail Competitive, Direct-to-Customer, Wellness, or Balanced. | E4: Scenario buttons are implemented as a dropdown in B4. Choose: Max Farmer, Max SHG, Lowest Investment, Market Penetration, Retail Competitive, Direct-to-Customer, Wellness, or Balanced. | F4: Scenario buttons are implemented as a dropdown in B4. Choose: Max Farmer, Max SHG, Lowest Investment, Market Penetration, Retail Competitive, Direct-to-Customer, Wellness, or Balanced. | G4: Scenario buttons are implemented as a dropdown in B4. Choose: Max Farmer, Max SHG, Lowest Investment, Market Penetration, Retail Competitive, Direct-to-Customer, Wellness, or Balanced. | H4: Scenario buttons are implemented as a dropdown in B4. Choose: Max Farmer, Max SHG, Lowest Investment, Market Penetration, Retail Competitive, Direct-to-Customer, Wellness, or Balanced. | I4: Scenario buttons are implemented as a dropdown in B4. Choose: Max Farmer, Max SHG, Lowest Investment, Market Penetration, Retail Competitive, Direct-to-Customer, Wellness, or Balanced. | J4: Scenario buttons are implemented as a dropdown in B4. Choose: Max Farmer, Max SHG, Lowest Investment, Market Penetration, Retail Competitive, Direct-to-Customer, Wellness, or Balanced. | K4: Scenario buttons are implemented as a dropdown in B4. Choose: Max Farmer, Max SHG, Lowest Investment, Market Penetration, Retail Competitive, Direct-to-Customer, Wellness, or Balanced. | L4: Scenario buttons are implemented as a dropdown in B4. Choose: Max Farmer, Max SHG, Lowest Investment, Market Penetration, Retail Competitive, Direct-to-Customer, Wellness, or Balanced. | M4: Scenario buttons are implemented as a dropdown in B4. Choose: Max Farmer, Max SHG, Lowest Investment, Market Penetration, Retail Competitive, Direct-to-Customer, Wellness, or Balanced. | N4: Scenario buttons are implemented as a dropdown in B4. Choose: Max Farmer, Max SHG, Lowest Investment, Market Penetration, Retail Competitive, Direct-to-Customer, Wellness, or Balanced.
A6: Optimised Recommendation
A7: Best pathway | B7: =INDEX('03 Pathway_Optimiser'!$A$4:$A$10,MATCH(1,'03 Pathway_Optimiser'!$O$4:$O$10,0)) -> P4 SHG Sourcing + SJ Processing + Retail | D7: Farmer price ₹/kg | E7: =INDEX('03 Pathway_Optimiser'!$C$4:$C$10,MATCH(1,'03 Pathway_Optimiser'!$O$4:$O$10,0)) -> 135 | G7: SHG net gain ₹/kg | H7: =INDEX('03 Pathway_Optimiser'!$G$4:$G$10,MATCH(1,'03 Pathway_Optimiser'!$O$4:$O$10,0)) -> 42 | J7: SHG monthly earning | K7: =INDEX('03 Pathway_Optimiser'!$I$4:$I$10,MATCH(1,'03 Pathway_Optimiser'!$O$4:$O$10,0)) -> 16800 | M7: Investment | N7: =INDEX('03 Pathway_Optimiser'!$J$4:$J$10,MATCH(1,'03 Pathway_Optimiser'!$O$4:$O$10,0)) -> 225000
A8: Description | B8: =INDEX('03 Pathway_Optimiser'!$B$4:$B$10,MATCH(1,'03 Pathway_Optimiser'!$O$4:$O$10,0)) -> SHG owns aggregation; SJ processing; sells through retailers with competitive price. | D8: Market fit | E8: =INDEX('03 Pathway_Optimiser'!$K$4:$K$10,MATCH(1,'03 Pathway_Optimiser'!$O$4:$O$10,0)) -> 5 | G8: Risk | H8: =INDEX('03 Pathway_Optimiser'!$L$4:$L$10,MATCH(1,'03 Pathway_Optimiser'!$O$4:$O$10,0)) -> 2 | J8: Demand | K8: =INDEX('03 Pathway_Optimiser'!$M$4:$M$10,MATCH(1,'03 Pathway_Optimiser'!$O$4:$O$10,0)) -> 5 | M8: Score | N8: =INDEX('03 Pathway_Optimiser'!$N$4:$N$10,MATCH(1,'03 Pathway_Optimiser'!$O$4:$O$10,0)) -> 519
A9: Edit inputs in | B9: 01 Scenario_Editor | D9: Edit node rates in | E9: 02 Nodes_Economics | G9: Review ranking in | H9: 03 Pathway_Optimiser | J9: Investment steps in | K9: 04 Investment_Planner | M9: Source data in | N9: 05 Source_Snapshot
A10: Primary decision | B10: Prioritise SHG direct + retail mix when market access is available; use SJ as quality/process facilitator.
A12: Current Pathways – visual flow cards with node price points | B12: Current Pathways – visual flow cards with node price points | C12: Current Pathways – visual flow cards with node price points | D12: Current Pathways – visual flow cards with node price points | E12: Current Pathways – visual flow cards with node price points | F12: Current Pathways – visual flow cards with node price points | G12: Current Pathways – visual flow cards with node price points | H12: Current Pathways – visual flow cards with node price points | I12: Current Pathways – visual flow cards with node price points | J12: Current Pathways – visual flow cards with node price points | K12: Current Pathways – visual flow cards with node price points | L12: Current Pathways – visual flow cards with node price points | M12: Current Pathways – visual flow cards with node price points | N12: Current Pathways – visual flow cards with node price points
A14: P1 Conventional | B14: Farmer Dried ₹120/kg | C14: → | D14: Sourcing Trader ₹135/kg | E14: → | F14: Processing Unit ₹180/kg | G14: → | H14: Distributor ₹200/kg | I14: → | J14: Retailer ₹240/kg | K14: → | L14: Customer | M14: Trader-led, low farmer/SHG capture
A18: P2 Seba Jagat Retail | B18: Farmer Dried ₹120/kg | C18: → | D18: Trader/SHG ₹135/kg | E18: → | F18: SJ Processing ₹180/kg | G18: → | H18: Distribution ₹200/kg | I18: → | J18: Retailer ₹240/kg | K18: → | L18: Customer | M18: SJ facilitates processing, not profit maximiser
A22: P3 SHG Direct | B22: Farmer Dried ₹135/kg | C22: → | D22: Women SHG Sourcing ₹145/kg | E22: → | F22: SHG/SJ Processing ₹190/kg | G22: → | H22: Women Network ₹250/kg | I22: → | J22: Customer | L22: Highest retained value if demand is built
A27: Pathway Ranking under selected scenario
A28: Rank | B28: Pathway | C28: Farmer ₹/kg | D28: SHG ₹/kg | E28: SHG monthly ₹ | F28: Investment ₹ | G28: Market fit | H28: Score | J28: How to use the tool
A29: ='03 Pathway_Optimiser'!O4 -> 6 | B29: ='03 Pathway_Optimiser'!A4 -> P1 Conventional | C29: ='03 Pathway_Optimiser'!C4 -> 120 | D29: ='03 Pathway_Optimiser'!G4 -> 0 | E29: ='03 Pathway_Optimiser'!I4 -> 0 | F29: ='03 Pathway_Optimiser'!J4 -> 0 | G29: ='03 Pathway_Optimiser'!K4 -> 4 | H29: ='03 Pathway_Optimiser'!N4 -> 210 | J29: 1 | K29: Change scenario in B4 or weights in Scenario_Editor.
A30: ='03 Pathway_Optimiser'!O5 -> 7 | B30: ='03 Pathway_Optimiser'!A5 -> P2 SJ Processing via Retail | C30: ='03 Pathway_Optimiser'!C5 -> 120 | D30: ='03 Pathway_Optimiser'!G5 -> 5 | E30: ='03 Pathway_Optimiser'!I5 -> 1875 | F30: ='03 Pathway_Optimiser'!J5 -> 250000 | G30: ='03 Pathway_Optimiser'!K5 -> 3 | H30: ='03 Pathway_Optimiser'!N5 -> 180 | J30: 2 | K30: Edit prices/costs in Scenario_Editor, Nodes_Economics or Pathway_Optimiser.
A31: ='03 Pathway_Optimiser'!O6 -> 4 | B31: ='03 Pathway_Optimiser'!A6 -> P3 SHG Direct Basic | C31: ='03 Pathway_Optimiser'!C6 -> 135 | D31: ='03 Pathway_Optimiser'!G6 -> 5 | E31: ='03 Pathway_Optimiser'!I6 -> 1250 | F31: ='03 Pathway_Optimiser'!J6 -> 150000 | G31: ='03 Pathway_Optimiser'!K6 -> 4 | H31: ='03 Pathway_Optimiser'!N6 -> 320 | J31: 3 | K31: Compare SHG monthly earning, investment and risk.
A32: ='03 Pathway_Optimiser'!O7 -> 1 | B32: ='03 Pathway_Optimiser'!A7 -> P4 SHG Sourcing + SJ Processing + Retail | C32: ='03 Pathway_Optimiser'!C7 -> 135 | D32: ='03 Pathway_Optimiser'!G7 -> 42 | E32: ='03 Pathway_Optimiser'!I7 -> 16800 | F32: ='03 Pathway_Optimiser'!J7 -> 225000 | G32: ='03 Pathway_Optimiser'!K7 -> 5 | H32: ='03 Pathway_Optimiser'!N7 -> 519 | J32: 4 | K32: Use lowest investment route first, then shift SHGs into processing/packing/distribution after demand is proven.
A33: ='03 Pathway_Optimiser'!O8 -> 4 | B33: ='03 Pathway_Optimiser'!A8 -> P5 SHG Full Chain Retail | C33: ='03 Pathway_Optimiser'!C8 -> 140 | D33: ='03 Pathway_Optimiser'!G8 -> 45 | E33: ='03 Pathway_Optimiser'!I8 -> 15750 | F33: ='03 Pathway_Optimiser'!J8 -> 450000 | G33: ='03 Pathway_Optimiser'!K8 -> 4 | H33: ='03 Pathway_Optimiser'!N8 -> 320 | J33: 5 | K33: Seba Jagat should facilitate quality, SOPs, processing access, FSSAI/testing and market discipline.
A34: ='03 Pathway_Optimiser'!O9 -> 2 | B34: ='03 Pathway_Optimiser'!A9 -> P6 SHG Direct + Retail Mix | C34: ='03 Pathway_Optimiser'!C9 -> 140 | D34: ='03 Pathway_Optimiser'!G9 -> 42.8 | E34: ='03 Pathway_Optimiser'!I9 -> 16050 | F34: ='03 Pathway_Optimiser'!J9 -> 350000 | G34: ='03 Pathway_Optimiser'!K9 -> 5 | H34: ='03 Pathway_Optimiser'!N9 -> 475.6 | J34: 6 | K34: The optimiser is a decision aid; verify demand and cash-flow before committing capital.
A35: ='03 Pathway_Optimiser'!O10 -> 3 | B35: ='03 Pathway_Optimiser'!A10 -> P7 Wellness Premium Small Batch | C35: ='03 Pathway_Optimiser'!C10 -> 135 | D35: ='03 Pathway_Optimiser'!G10 -> 180 | E35: ='03 Pathway_Optimiser'!I10 -> 18000 | F35: ='03 Pathway_Optimiser'!J10 -> 600000 | G35: ='03 Pathway_Optimiser'!K10 -> 3 | H35: ='03 Pathway_Optimiser'!N10 -> 360

Sheet 01 Scenario_Editor
A1: Turmeric Value Chain Scenario Editor
A3: Common editable assumptions | B3: Value | J3: Selected scenario weights used by optimiser
A4: Monthly dried turmeric available for modelling (kg) | B4: 500 | J4: Selected scenario | K4: Farmer gain | L4: SHG gain | M4: Market fit | N4: Investment penalty | O4: Risk penalty | P4: Demand strength | Q4: Note
A5: Baseline farmer sale price (₹/kg dried) | B5: 120 | J5: ='00 Dashboard'!B4 -> Balanced Farmer + SHG Benefit | K5: =INDEX($B$22:$B$29,MATCH($J$5,$A$22:$A$29,0)) -> 4 | L5: =INDEX($C$22:$C$29,MATCH($J$5,$A$22:$A$29,0)) -> 4 | M5: =INDEX($D$22:$D$29,MATCH($J$5,$A$22:$A$29,0)) -> 3 | N5: =INDEX($E$22:$E$29,MATCH($J$5,$A$22:$A$29,0)) -> 2 | O5: =INDEX($F$22:$F$29,MATCH($J$5,$A$22:$A$29,0)) -> 2 | P5: =INDEX($G$22:$G$29,MATCH($J$5,$A$22:$A$29,0)) -> 2 | Q5: =INDEX($H$22:$H$29,MATCH($J$5,$A$22:$A$29,0)) -> Balanced inclusive village economy
A6: Fresh-to-dry conversion ratio (fresh kg per 1 kg dry) | B6: 5
A7: Dry-to-powder recovery (%) | B7: 0.95
A8: Processing cost (₹/kg dry input) | B8: 20
A9: Polishing/cleaning/handling cost (₹/kg) | B9: 5
A10: Packaging cost 50g/100g/200g/1kg weighted avg (₹/kg) | B10: 35
A11: Distribution cost retail route (₹/kg) | B11: 15
A12: Distribution cost direct route (₹/kg) | B12: 8
A13: Retailer/dealer margin expected (₹/kg) | B13: 40
A14: Women network commission/direct selling cost (₹/kg) | B14: 20
A15: Working capital days | B15: 45
A16: Interest / opportunity cost per annum | B16: 0.12
A17: Minimum acceptable farmer price (₹/kg dried) | B17: 135
A18: Selected scenario weights used by optimiser
A19: Selected Weight | B19: Farmer gain | C19: SHG gain | D19: Market fit | E19: Investment penalty | F19: Risk penalty | G19: Demand strength | H19: Scenario linked from Dashboard
A20: Scenario weights - editable; Dashboard selector uses these rows
A21: Scenario | B21: Farmer gain weight | C21: SHG gain weight | D21: Market fit weight | E21: Investment penalty | F21: Risk penalty | G21: Demand weight | H21: Note
A22: Maximise Farmer Income | B22: 5 | C22: 2 | D22: 2 | E22: 1 | F22: 2 | G22: 1 | H22: Prioritises dried price to farmers and SHG procurement
A23: Maximise SHG Income | B23: 2 | C23: 5 | D23: 2 | E23: 1 | F23: 2 | G23: 1 | H23: Prioritises SHG net margin and owned stages
A24: Lowest Investment Path | B24: 2 | C24: 2 | D24: 2 | E24: 5 | F24: 3 | G24: 1 | H24: Prioritises manageable capital and low risk
A25: Highest Market Penetration | B25: 2 | C25: 2 | D25: 5 | E25: 2 | F25: 2 | G25: 4 | H25: Prioritises low-price/high-demand SKUs
A26: Retail Competitive Price | B26: 2 | C26: 3 | D26: 5 | E26: 2 | F26: 2 | G26: 3 | H26: Matches local kirana economics
A27: Direct-to-Customer Strategy | B27: 3 | C27: 5 | D27: 3 | E27: 2 | F27: 3 | G27: 2 | H27: Pushes women network/direct sales
A28: Wellness Product Strategy | B28: 2 | C28: 5 | D28: 3 | E28: 3 | F28: 4 | G28: 2 | H28: Premium products, lower volume, higher branding needs
A29: Balanced Farmer + SHG Benefit | B29: 4 | C29: 4 | D29: 3 | E29: 2 | F29: 2 | G29: 2 | H29: Balanced inclusive village economy
A31: Flexible SHG stage ownership options
A32: Stage | B32: Can SHG own? | C32: Low investment mode | D32: Higher investment mode | E32: Typical cost ₹/kg | F32: Market/control benefit | G32: Risk | H32: Notes
A33: Sourcing/Aggregation | B33: Yes | C33: Village procurement + grading | D33: Digital weighing + aggregation centre | E33: 3 | F33: Higher farmer price, traceability | G33: Low | H33: Good first move
A34: Boiling/Drying | B34: Yes | C34: Shared dryers/sun-drying protocol | D34: Improved dryer and moisture control | E34: 8 | F34: Improves quality and price | G34: Medium | H34: Needs SOP
A35: Processing/Powdering | B35: Yes | C35: Use Seba Jagat unit as service | D35: Own pulveriser/processing unit | E35: 20 | F35: Captures processing margin | G35: Medium | H35: Start service-based
A36: Packing/Branding | B36: Yes | C36: Manual/semi-auto packing | D36: FSSAI, branding, sealing, coding | E36: 35 | F36: Captures SKU premium | G36: Medium | H36: Quality consistency important
A37: Distribution | B37: Yes | C37: Women sales network | D37: Dealer/retailer network | E37: 8 | F37: Improves reach | G37: Medium | H37: Needs follow-up discipline
A38: Retail/Direct Sales | B38: Yes | C38: SHG/women network orders | D38: Retail kiosks/e-commerce/local institutions | E38: 20 | F38: Maximum retained value | G38: High | H38: Demand building needed
A39: Wellness Value Addition | B39: Possible | C39: Small batches | D39: Certified premium products | E39: 80 | F39: Higher price realization | G39: High | H39: Only after base market fit

Sheet 02 Nodes_Economics
A1: Current Flow Map and Node Economics
A3: Pathway | B3: Node Order | C3: Actor / Node | D3: Product handled | E3: Buys at ₹/kg | F3: Adds cost ₹/kg | G3: Sells at ₹/kg | H3: Margin ₹/kg | I3: Monthly volume kg | J3: Monthly earning ₹ | K3: Beneficiary | L3: Editable Notes
A4: P1 Conventional | B4: 1 | C4: Farmer | D4: Dried turmeric | F4: 0 | G4: 120 | H4: =G4-E4-F4 -> 120 | I4: 500 | J4: =H4*I4 -> 60000 | K4: Farmer | L4: Current farmer dried sale
A5: P1 Conventional | B5: 2 | C5: Sourcing Trader | D5: Dried turmeric | E5: 120 | F5: 5 | G5: 135 | H5: =G5-E5-F5 -> 10 | I5: 500 | J5: =H5*I5 -> 5000 | K5: Trader | L5: Trader aggregation margin
A6: P1 Conventional | B6: 3 | C6: Processing Unit | D6: Loose/processed powder | E6: 135 | F6: 25 | G6: 180 | H6: =G6-E6-F6 -> 20 | I6: 475 | J6: =H6*I6 -> 9500 | K6: Processor | L6: Processing and recovery included
A7: P1 Conventional | B7: 4 | C7: Distributor | D7: Packed/loose powder | E7: 180 | F7: 10 | G7: 200 | H7: =G7-E7-F7 -> 10 | I7: 475 | J7: =H7*I7 -> 4750 | K7: Distributor | L7: Distribution margin
A8: P1 Conventional | B8: 5 | C8: Retailer | D8: Packed powder | E8: 200 | F8: 0 | G8: 240 | H8: =G8-E8-F8 -> 40 | I8: 475 | J8: =H8*I8 -> 19000 | K8: Retailer | L8: Retail consumer price
A9: P2 Seba Jagat Retail | B9: 1 | C9: Farmer | D9: Dried turmeric | F9: 0 | G9: 120 | H9: =G9-E9-F9 -> 120 | I9: 500 | J9: =H9*I9 -> 60000 | K9: Farmer | L9: Current baseline
A10: P2 Seba Jagat Retail | B10: 2 | C10: Trader/SHG Aggregator | D10: Dried turmeric | E10: 120 | F10: 5 | G10: 135 | H10: =G10-E10-F10 -> 10 | I10: 500 | J10: =H10*I10 -> 5000 | K10: Trader/SHG | L10: Aggregation can shift to SHG
A11: P2 Seba Jagat Retail | B11: 3 | C11: Seba Jagat Processing Centre | D11: Powder | E11: 135 | F11: 20 | G11: 180 | H11: =G11-E11-F11 -> 25 | I11: 475 | J11: =H11*I11 -> 11875 | K11: Facilitator/SHG | L11: SJ as facilitator; surplus can support SHG operations
A12: P2 Seba Jagat Retail | B12: 4 | C12: Distribution Channel | D12: Packed powder | E12: 180 | F12: 15 | G12: 200 | H12: =G12-E12-F12 -> 5 | I12: 475 | J12: =H12*I12 -> 2375 | K12: Distributor/SHG | L12: SHG may own distribution
A13: P2 Seba Jagat Retail | B13: 5 | C13: Retailer | D13: SKU packs | E13: 200 | F13: 0 | G13: 240 | H13: =G13-E13-F13 -> 40 | I13: 475 | J13: =H13*I13 -> 19000 | K13: Retailer | L13: Retailer margin needed
A14: P3 SHG Direct | B14: 1 | C14: Farmer | D14: Dried turmeric | F14: 0 | G14: 135 | H14: =G14-E14-F14 -> 135 | I14: 500 | J14: =H14*I14 -> 67500 | K14: Farmer | L14: Improved farmer price target
A15: P3 SHG Direct | B15: 2 | C15: Women SHG Sourcing | D15: Dried turmeric | E15: 135 | F15: 3 | G15: 145 | H15: =G15-E15-F15 -> 7 | I15: 500 | J15: =H15*I15 -> 3500 | K15: Women SHG | L15: Aggregation/grading
A16: P3 SHG Direct | B16: 3 | C16: Women SHG Processing | D16: Powder | E16: 145 | F16: 20 | G16: 190 | H16: =G16-E16-F16 -> 25 | I16: 475 | J16: =H16*I16 -> 11875 | K16: Women SHG | L16: Processing service or own unit
A17: P3 SHG Direct | B17: 4 | C17: Women Network / Direct Retail | D17: Packed turmeric | E17: 190 | F17: 43 | G17: 250 | H17: =G17-E17-F17 -> 17 | I17: 475 | J17: =H17*I17 -> 8075 | K17: Women SHG | L17: Packing + direct selling
A18: P3 SHG Direct | B18: 5 | C18: Customer | D18: Final consumption | E18: 250 | F18: 0 | G18: 250 | H18: =G18-E18-F18 -> 0 | I18: 475 | J18: =H18*I18 -> 0 | K18: Customer | L18: Consumer price point

Sheet 03 Pathway_Optimiser
A1: Pathway Optimiser - compares current and improved turmeric value-chain routes
A3: Pathway | B3: Description | C3: Farmer sale price ₹/kg | D3: Farmer gain vs baseline | E3: SHG gross margin ₹/kg | F3: SHG operating cost ₹/kg | G3: SHG net gain ₹/kg | H3: Model volume kg/month | I3: SHG monthly earning ₹ | J3: Investment required ₹ | K3: Market fit 1-5 | L3: Risk 1-5 | M3: Demand strength 1-5 | N3: Optimisation score | O3: Rank
A4: P1 Conventional | B4: Baseline trader-led route. SHG has no value capture. | C4: 120 | D4: =C4-'01 Scenario_Editor'!$B$5 -> 0 | E4: 0 | F4: 0 | G4: =E4-F4 -> 0 | H4: ='01 Scenario_Editor'!$B$4 -> 500 | I4: =G4*H4 -> 0 | J4: 0 | K4: 4 | L4: 1 | M4: 4 | N4: =D4*'01 Scenario_Editor'!$K$5+G4*0.5*'01 Scenario_Editor'!$L$5+K4*20*'01 Scenario_Editor'!$M$5-(J4/10000)*'01 Scenario_Editor'!$N$5-L4*20*'01 Scenario_Editor'!$O$5+M4*20*'01 Scenario_Editor'!$P$5+IF(G4=0,-150,0) -> 210 | O4: =RANK(N4,$N$4:$N$10,0) -> 6
A5: P2 SJ Processing via Retail | B5: Farmer sells as current; Seba Jagat processes and sells via retail/dealer chain. | C5: 120 | D5: =C5-'01 Scenario_Editor'!$B$5 -> 0 | E5: 45 | F5: ='01 Scenario_Editor'!$B$9+'01 Scenario_Editor'!$B$10 -> 40 | G5: =E5-F5 -> 5 | H5: ='01 Scenario_Editor'!$B$4*0.75 -> 375 | I5: =G5*H5 -> 1875 | J5: 250000 | K5: 3 | L5: 2 | M5: 3 | N5: =D5*'01 Scenario_Editor'!$K$5+G5*0.5*'01 Scenario_Editor'!$L$5+K5*20*'01 Scenario_Editor'!$M$5-(J5/10000)*'01 Scenario_Editor'!$N$5-L5*20*'01 Scenario_Editor'!$O$5+M5*20*'01 Scenario_Editor'!$P$5+IF(G5=0,-150,0) -> 180 | O5: =RANK(N5,$N$4:$N$10,0) -> 7
A6: P3 SHG Direct Basic | B6: SHG buys dried turmeric at fairer price, processes through SJ unit, sells directly. | C6: 135 | D6: =C6-'01 Scenario_Editor'!$B$5 -> 15 | E6: 100 | F6: ='01 Scenario_Editor'!$B$8+'01 Scenario_Editor'!$B$10+'01 Scenario_Editor'!$B$13 -> 95 | G6: =E6-F6 -> 5 | H6: ='01 Scenario_Editor'!$B$4*0.5 -> 250 | I6: =G6*H6 -> 1250 | J6: 150000 | K6: 4 | L6: 3 | M6: 4 | N6: =D6*'01 Scenario_Editor'!$K$5+G6*0.5*'01 Scenario_Editor'!$L$5+K6*20*'01 Scenario_Editor'!$M$5-(J6/10000)*'01 Scenario_Editor'!$N$5-L6*20*'01 Scenario_Editor'!$O$5+M6*20*'01 Scenario_Editor'!$P$5+IF(G6=0,-150,0) -> 320 | O6: =RANK(N6,$N$4:$N$10,0) -> 4
A7: P4 SHG Sourcing + SJ Processing + Retail | B7: SHG owns aggregation; SJ processing; sells through retailers with competitive price. | C7: 135 | D7: =C7-'01 Scenario_Editor'!$B$5 -> 15 | E7: 85 | F7: ='01 Scenario_Editor'!$B$8+'01 Scenario_Editor'!$B$11+'01 Scenario_Editor'!$B$12 -> 43 | G7: =E7-F7 -> 42 | H7: ='01 Scenario_Editor'!$B$4*0.8 -> 400 | I7: =G7*H7 -> 16800 | J7: 225000 | K7: 5 | L7: 2 | M7: 5 | N7: =D7*'01 Scenario_Editor'!$K$5+G7*0.5*'01 Scenario_Editor'!$L$5+K7*20*'01 Scenario_Editor'!$M$5-(J7/10000)*'01 Scenario_Editor'!$N$5-L7*20*'01 Scenario_Editor'!$O$5+M7*20*'01 Scenario_Editor'!$P$5+IF(G7=0,-150,0) -> 519 | O7: =RANK(N7,$N$4:$N$10,0) -> 1
A8: P5 SHG Full Chain Retail | B8: SHG owns sourcing, processing, packing and distribution; retailer remains final outlet. | C8: 140 | D8: =C8-'01 Scenario_Editor'!$B$5 -> 20 | E8: 120 | F8: ='01 Scenario_Editor'!$B$8+'01 Scenario_Editor'!$B$9+'01 Scenario_Editor'!$B$10+'01 Scenario_Editor'!$B$11 -> 75 | G8: =E8-F8 -> 45 | H8: ='01 Scenario_Editor'!$B$4*0.7 -> 350 | I8: =G8*H8 -> 15750 | J8: 450000 | K8: 4 | L8: 4 | M8: 4 | N8: =D8*'01 Scenario_Editor'!$K$5+G8*0.5*'01 Scenario_Editor'!$L$5+K8*20*'01 Scenario_Editor'!$M$5-(J8/10000)*'01 Scenario_Editor'!$N$5-L8*20*'01 Scenario_Editor'!$O$5+M8*20*'01 Scenario_Editor'!$P$5+IF(G8=0,-150,0) -> 320 | O8: =RANK(N8,$N$4:$N$10,0) -> 4
A9: P6 SHG Direct + Retail Mix | B9: 60% direct women network + 40% retail route; balances volume and margin. | C9: 140 | D9: =C9-'01 Scenario_Editor'!$B$5 -> 20 | E9: 130 | F9: ='01 Scenario_Editor'!$B$8+'01 Scenario_Editor'!$B$9+'01 Scenario_Editor'!$B$10+('01 Scenario_Editor'!$B$12*0.4)+'01 Scenario_Editor'!$B$13*0.6 -> 87.2 | G9: =E9-F9 -> 42.8 | H9: ='01 Scenario_Editor'!$B$4*0.75 -> 375 | I9: =G9*H9 -> 16050 | J9: 350000 | K9: 5 | L9: 3 | M9: 5 | N9: =D9*'01 Scenario_Editor'!$K$5+G9*0.5*'01 Scenario_Editor'!$L$5+K9*20*'01 Scenario_Editor'!$M$5-(J9/10000)*'01 Scenario_Editor'!$N$5-L9*20*'01 Scenario_Editor'!$O$5+M9*20*'01 Scenario_Editor'!$P$5+IF(G9=0,-150,0) -> 475.6 | O9: =RANK(N9,$N$4:$N$10,0) -> 2
A10: P7 Wellness Premium Small Batch | B10: Value-added/wellness products at premium price; higher branding and demand risk. | C10: 135 | D10: =C10-'01 Scenario_Editor'!$B$5 -> 15 | E10: 300 | F10: 120 | G10: =E10-F10 -> 180 | H10: ='01 Scenario_Editor'!$B$4*0.2 -> 100 | I10: =G10*H10 -> 18000 | J10: 600000 | K10: 3 | L10: 5 | M10: 2 | N10: =D10*'01 Scenario_Editor'!$K$5+G10*0.5*'01 Scenario_Editor'!$L$5+K10*20*'01 Scenario_Editor'!$M$5-(J10/10000)*'01 Scenario_Editor'!$N$5-L10*20*'01 Scenario_Editor'!$O$5+M10*20*'01 Scenario_Editor'!$P$5+IF(G10=0,-150,0) -> 360 | O10: =RANK(N10,$N$4:$N$10,0) -> 3

Sheet 04 Investment_Planner
A1: Investment Planner - minimal investment route before owning every stage
A3: Stage | B3: Investment Item | C3: Low-cost option ₹ | D3: Higher-control option ₹ | E3: Recommended for Phase 1? | F3: Why | G3: Operating cost impact ₹/kg | H3: Owner | I3: Priority | J3: Notes
A4: Sourcing | B4: Digital weighing scale, crates, moisture meter | C4: 25000 | D4: 75000 | E4: Yes | F4: Improves grading and farmer trust | G4: 3 | H4: SHG | I4: High | J4: Start here
A5: Drying | B5: Improved drying mats/trays, SOP, storage bins | C5: 50000 | D5: 250000 | E5: Yes | F5: Improves colour and quality | G5: 8 | H5: SHG | I5: High | J5: Avoid moisture risk
A6: Processing | B6: Use Seba Jagat unit as service | C6: 0 | D6: 400000 | E6: Yes - service mode | F6: Avoids heavy capex initially | G6: 20 | H6: SJ facilitated/SHG | I6: High | J6: Shift to own unit after demand proven
A7: Packing | B7: Sealer, labels, pouches, batch coding | C7: 60000 | D7: 250000 | E7: Yes | F7: Small SKUs require reliable packing | G7: 35 | H7: SHG | I7: High | J7: Focus 10g/20g/100g
A8: Distribution | B8: Women network kits, retail route plan | C8: 40000 | D8: 150000 | E8: Yes | F8: Direct channel adds margin | G8: 8 | H8: SHG | I8: Medium | J8: Need monthly follow-up
A9: Retail | B9: Display boxes, village point-of-sale | C9: 30000 | D9: 200000 | E9: Selective | F9: Useful after repeat demand | G9: 20 | H9: SHG/Women entrepreneurs | I9: Medium | J9: Pilot with 10-20 outlets
A10: Quality/Compliance | B10: FSSAI, testing, brand system | C10: 50000 | D10: 200000 | E10: Yes | F10: Builds retailer and consumer confidence | G10: 5 | H10: Seba Jagat facilitator | I10: High | J10: SJ should support
A11: Wellness Products | B11: R&D, recipes, premium packaging | C11: 100000 | D11: 500000 | E11: Later | F11: Higher price but higher risk | G11: 80 | H11: SHG/SJ support | I11: Low | J11: Phase 2/3

Sheet 05 Source_Snapshot
A1: Source Snapshot from RT Data.xlsx
A3: Current chain rates
A4: Stage | B4: Product Form | C4: Buyer Type | D4: Market Location | E4: Purchase Rate ₹/kg | F4: Selling Rate ₹/kg | G4: Volume | H4: Packaging
A5: Farmer Level | B5: Fresh Raw Turmeric | C5: Agent/Trader | D5: Kandhamal | F5: 85
A6: Drying Stage | B6: Dried Fingers | C6: Wholesaler | D6: Kalahandi | E6: 135 | F6: 160 | G6: 50 Qtl | H6: Sack
A7: Processing Stage | B7: Polished Fingers | C7: Distributor | D7: Kalahandi | E7: 155 | F7: 180 | H7: Bagged
A8: Powder Processing | B8: Turmeric Powder | C8: Retailer | D8: Kalahandi | E8: 180 | F8: 200 | H8: Retail Pack
A9: Retail Market | B9: Packed Powder | C9: Consumer | D9: Kalahandi | E9: 200 | F9: 250 | H9: 100g/250g/500g
A12: Market observations
A13: Parameter | B13: Observation
A14: Main Brands | B14: Bharat Masala, Everest, Ruchi
A15: Most Preferred Brand | B15: Bharat Masala
A16: Reason for Preference | B16: Higher retailer margins
A17: Average Turmeric Sold per Kirana Store | B17: 10 kg/month approx
A18: Average Purchase Quantity | B18: 15 kg from dealers approx
A19: Fast Moving SKUs | B19: ₹5/10g, ₹10/20g, ₹46/100g, ₹76/200g
A20: Retailer Margin - Bharat Masala | B20: ₹2–3 per packet
A21: Retailer Feedback on Seba Jagat | B21: Trusted among tribal communities; improve color, price competitiveness, packaging and follow-up
A22: Key Insight | B22: Retailers prioritize profitability over brand loyalty
A23: Consumer Preference | B23: Small affordable sachets
A24: Market Opportunity | B24: Strong rural demand for low-ticket packs
A27: Price points
A28: Product/SKU | B28: Seba Jagat retailer price | C28: Bharat/Everest retailer purchase | D28: Retailer margin | E28: Consumer price | F28: Equivalent ₹/kg
A29: Dried turmeric - farmer | B29: 120 | F29: 120
A30: Dried turmeric - trader/SHG | B30: 135 | F30: 135
A31: Loose powder | B31: 180 | F31: 180
A32: Seba Jagat 50g | B32: 25 | E32: 25 | F32: 500
A33: Seba Jagat 100g | B33: 50 | E33: 50 | F33: 500
A34: Seba Jagat 200g | B34: 90 | E34: 90 | F34: 450
A35: Seba Jagat 1kg | B35: 200 | E35: 200 | F35: 200
A36: Bharat 10g | C36: 4 | D36: 1 | E36: 5 | F36: 500
A37: Bharat 20g | C37: 8.75 | D37: 1.25 | E37: 10 | F37: 500
A38: Bharat 100g | C38: 44 | D38: 2 | E38: 46 | F38: 460
A39: Bharat 200g | C39: 74 | D39: 2 | E39: 76 | F39: 380
